[
  {
    "id": 1,
    "weapon": "ICR",
    "image": "https://gamewith-en.akamaized.net/img/86dc60a90c75c2fac35e07f3f25736dc.jpg",
    "count": 0
  },
  {
    "id": 2,
    "weapon": "KN-57",
    "image": "https://gamewith-en.akamaized.net/article_tools/cod-black-ops4/gacha/761.png",
    "count": 0
  },
  {
    "id": 3,
    "weapon": "RAMPART 17",
    "image": "https://gamewith-en.akamaized.net/article_tools/cod-black-ops4/gacha/790.png",
    "count": 0
  },
  {
    "id": 4,
    "weapon": "VAPR-XKG",
    "image": "https://gamewith-en.akamaized.net/article_tools/cod-black-ops4/gacha/791.png",
    "count": 0
  },
  {
    "id": 5,
    "weapon": "Maddox RFB",
    "image": "https://gamewith-en.akamaized.net/article_tools/cod-black-ops4/gacha/793.png",
    "count": 0
  },
  {
    "id": 6,
    "weapon": "SWAT RFT",
    "image": "https://gamewith-en.akamaized.net/img/e51f7e379e6a8fd0022b6fa21657e1f4.jpg",
    "count": 0
  },
  {
    "id": 7,
    "weapon": "MX9",
    "image": "https://gamewith-en.akamaized.net/article_tools/cod-black-ops4/gacha/796.png",
    "count": 0
  },
  {
    "id": 8,
    "weapon": "GKS",
    "image": "https://gamewith-en.akamaized.net/article_tools/cod-black-ops4/gacha/802.png",
    "count": 0
  },
  {
    "id": 9,
    "weapon": "SPITFIRE",
    "image": "https://gamewith-en.akamaized.net/article_tools/cod-black-ops4/gacha/801.png",
    "count": 0
  },
  {
    "id": 10,
    "weapon": "CORDITE",
    "image": "https://gamewith-en.akamaized.net/article_tools/cod-black-ops4/gacha/800.png",
    "count": 0
  },
  {
    "id": 11,
    "weapon": "SAUG 9MM",
    "image": "https://gamewith-en.akamaized.net/article_tools/cod-black-ops4/gacha/834.png",
    "count": 0
  },
  {
    "id": 12,
    "weapon": "DAEMON 3XB",
    "image": "https://gamewith-en.akamaized.net/img/2ad2af1055a9f89977faf633354278ab.jpg",
    "count": 0
  },
  {
    "id": 13,
    "weapon": "AUGER DMR",
    "image": "https://gamewith-en.akamaized.net/article_tools/cod-black-ops4/gacha/831.png",
    "count": 0
  },
  {
    "id": 14,
    "weapon": "ABR 223",
    "image": "https://gamewith-en.akamaized.net/article_tools/cod-black-ops4/gacha/841.png",
    "count": 0
  },
  {
    "id": 15,
    "weapon": "SWORDFISH",
    "image": "https://gamewith-en.akamaized.net/article_tools/cod-black-ops4/gacha/832.png",
    "count": 0
  },
  {
    "id": 16,
    "weapon": "TITAN",
    "image": "https://gamewith-en.akamaized.net/article_tools/cod-black-ops4/gacha/833.png",
    "count": 0
  },
  {
    "id": 17,
    "weapon": "HADES",
    "image": "https://gamewith-en.akamaized.net/article_tools/cod-black-ops4/gacha/836.png",
    "count": 0
  },
  {
    "id": 18,
    "weapon": "VKM 750",
    "image": "https://gamewith-en.akamaized.net/article_tools/cod-black-ops4/gacha/844.png",
    "count": 0
  },
  {
    "id": 19,
    "weapon": "PALADIN HB50",
    "image": "https://gamewith-en.akamaized.net/article_tools/cod-black-ops4/gacha/842.png",
    "count": 0
  },
  {
    "id": 20,
    "weapon": "OUTLAW",
    "image": "https://gamewith-en.akamaized.net/article_tools/cod-black-ops4/gacha/843.png",
    "count": 0
  },
  {
    "id": 21,
    "weapon": "SDM",
    "image": "https://gamewith-en.akamaized.net/article_tools/cod-black-ops4/gacha/840.png",
    "count": 0
  },
  {
    "id": 22,
    "weapon": "KOSHKA",
    "image": "https://gamewith-en.akamaized.net/article_tools/cod-black-ops4/gacha/839.png",
    "count": 0
  },
  {
    "id": 23,
    "weapon": "STRIFE",
    "image": "https://gamewith-en.akamaized.net/article_tools/cod-black-ops4/gacha/838.png",
    "count": 0
  },
  {
    "id": 24,
    "weapon": "RK7 GARRISON",
    "image": "https://gamewith-en.akamaized.net/article_tools/cod-black-ops4/gacha/837.png",
    "count": 0
  },
  {
    "id": 25,
    "weapon": "MOZU",
    "image": "https://gamewith-en.akamaized.net/article_tools/cod-black-ops4/gacha/849.png",
    "count": 0
  },
  {
    "id": 26,
    "weapon": "MOG 12",
    "image": "https://gamewith-en.akamaized.net/article_tools/cod-black-ops4/gacha/848.png",
    "count": 0
  },
  {
    "id": 27,
    "weapon": "SG12",
    "image": "https://gamewith-en.akamaized.net/article_tools/cod-black-ops4/gacha/847.png",
    "count": 0
  }
]
